[
    {
        "skill": "React",
        "level": "advanced",
        "color": "blue"
    },
    {
        "skill": "JavaScript",
        "level": "advanced",
        "color": "yellow"
    },
    {
        "skill": "HTML",
        "level": "beginner",
        "color": "orange"
    },
    {
        "skill": "CSS",
        "level": "intermediate",
        "color": "pink"
    },
    {
        "skill": "Node.js",
        "level": "advanced",
        "color": "green"
    },
    {
        "skill": "Python",
        "level": "beginner",
        "color": "purple"
    }
]